{
  "status": {
    "checked_at": "2026-06-28T06:00:22.507036",
    "listings": [
      {
        "name": "1 - New York New Jersey Stadium - AMERICAN DREAM",
        "available_inventory": 352,
        "is_available": true,
        "presell": true,
        "prices": [
          {
            "name": "General Pricing",
            "amount": 21122,
            "total": 24999
          }
        ]
      },
      {
        "name": "New York New Jersey Stadium - H Plaza Lot J ADA/Accessibility Parking - FIFA",
        "available_inventory": 0,
        "is_available": false,
        "presell": true,
        "prices": [
          {
            "name": "ADA Parking",
            "amount": 21122,
            "total": 24999
          }
        ]
      }
    ]
  }
}